sigalg/__init__.py
sigalg/core/__init__.py
sigalg/core/base/__init__.py
sigalg/core/base/event.py
sigalg/core/base/event_space.py
sigalg/core/base/feature_vector.py
sigalg/core/base/index.py
sigalg/core/base/probability_space.py
sigalg/core/base/sample_space.py
sigalg/core/base/time.py
sigalg/core/info/__init__.py
sigalg/core/info/plot_information_flow.py
sigalg/core/probability_measures/__init__.py
sigalg/core/probability_measures/probability_measure.py
sigalg/core/random_objects/__init__.py
sigalg/core/random_objects/operators.py
sigalg/core/random_objects/random_variable.py
sigalg/core/random_objects/random_vector.py
sigalg/core/sigma_algebras/__init__.py
sigalg/core/sigma_algebras/comparison.py
sigalg/core/sigma_algebras/filtered_sigma_algebra.py
sigalg/core/sigma_algebras/filtration.py
sigalg/core/sigma_algebras/lattice_operations.py
sigalg/core/sigma_algebras/sigma_algebra.py
sigalg/l2/__init__.py
sigalg/l2/base/__init__.py
sigalg/l2/base/l2.py
sigalg/processes/__init__.py
sigalg/processes/base/__init__.py
sigalg/processes/base/stochastic_process.py
sigalg/processes/base/trajectory.py
sigalg/processes/transforms/__init__.py
sigalg/processes/transforms/process_transforms.py
sigalg/processes/types/__init__.py
sigalg/processes/types/branching_process.py
sigalg/processes/types/brownian_motion.py
sigalg/processes/types/iid_process.py
sigalg/processes/types/markov_chain.py
sigalg/processes/types/poisson_process.py
sigalg/processes/types/random_walk.py
sigalg/stochastic_calculus/__init__.py
sigalg/stochastic_calculus/ito_integral.py
sigalg/validation/index_in.py
sigalg/validation/sample_space_mapping_in.py
sigalg/validation/time_in.py
sigalg-0.1.0.dist-info/licenses/LICENSE
sigalg-0.1.0.dist-info/METADATA
sigalg-0.1.0.dist-info/WHEEL
sigalg-0.1.0.dist-info/top_level.txt
sigalg-0.1.0.dist-info/RECORD
