Metadata-Version: 2.4
Name: sigalg
Version: 0.1.0
Summary: A Python package for measure-theoretic probability theory.
Author-email: John Myers <john@johnmyers-phd.com>
License: MIT License
Project-URL: Repository, https://github.com/jmyers7/sigalg
Keywords: probability,measure-theory,mathematics,stochastic-processes,martingales,quantitative-finance,sigma-algebra,random-variables,conditional-expectation,brownian-motion,stochastic-calculus,ito-integral,financial-mathematics,option-pricing,risk-neutral-measure
Classifier: Development Status :: 3 - Alpha
Classifier: Intended Audience :: Science/Research
Classifier: Topic :: Scientific/Engineering :: Mathematics
Classifier: License :: OSI Approved :: MIT License
Classifier: Programming Language :: Python :: 3
Classifier: Programming Language :: Python :: 3.10
Classifier: Programming Language :: Python :: 3.11
Classifier: Programming Language :: Python :: 3.12
Classifier: Programming Language :: Python :: 3.13
Requires-Python: >=3.10
License-File: LICENSE
Requires-Dist: numpy
Requires-Dist: pandas
Requires-Dist: matplotlib
Requires-Dist: scipy
Requires-Dist: scikit-learn
Requires-Dist: plotly
Requires-Dist: pydantic
Provides-Extra: dev
Requires-Dist: pytest; extra == "dev"
Requires-Dist: pytest-cov; extra == "dev"
Requires-Dist: black; extra == "dev"
Requires-Dist: mypy; extra == "dev"
Requires-Dist: flake8; extra == "dev"
Requires-Dist: isort; extra == "dev"
Requires-Dist: ruff; extra == "dev"
Dynamic: license-file
